stoel/__init__.py
stoel/config.py
stoel/crud.py
stoel/database.py
stoel/main.py
stoel/model.py
stoel/schemas.py
stoel/session.py
stoel/stoel.db
stoel-0.1.0.dist-info/WHEEL
stoel-0.1.0.dist-info/METADATA
stoel-0.1.0.dist-info/RECORD
